SimpleBattle/__init__.py
SimpleBattle/main.py
SimpleBattle/Character/__init__.py
SimpleBattle/Character/character.py
SimpleBattle/Character/npc.py
SimpleBattle/Character/player.py
SimpleBattle/Gameplay/__init__.py
SimpleBattle/Gameplay/combat.py
SimpleBattle/Gameplay/events.py
SimpleBattle/Gameplay/interface.py
SimpleBattle-0.0.2.dist-info/LICENSE.txt
SimpleBattle-0.0.2.dist-info/METADATA
SimpleBattle-0.0.2.dist-info/WHEEL
SimpleBattle-0.0.2.dist-info/top_level.txt
SimpleBattle-0.0.2.dist-info/RECORD
