Metadata-Version: 2.1
Name: SimpleBattle
Version: 0.0.2
Summary: Simple Battle is a turn-based battle simulator where players engage in combat with NPC opponents. 
Author-email: Zefeng Pei <zefengpei@gmail.com>, Jiakun Li <jacob.jiakunli@gmail.com>
Project-URL: Homepage, https://github.com/ZefengPei/533project_step3
Project-URL: Issues, https://github.com/ZefengPei/533project_step3/issues
Classifier: Programming Language :: Python :: 3
Classifier: License :: OSI Approved :: MIT License
Classifier: Operating System :: OS Independent
Requires-Python: >=3.8
License-File: LICENSE.txt
